[
  {
    "rank": 1,
    "text": "months before availing this benefit. The New Born Baby shall be automatically covered from birth under the Sum Insured available to the mother during the corresponding Policy Period, for up to 3 months of age. On attaining 3 months of age, the New Born Baby shall be covered only if specifically included in the Policy mid-term and requisite premium paid to the Company. Cover Maternity Expenses means; a) Medical treatment expenses traceable to childbirth (including complicated deliveries and caesarean sections incurred during Hospitalization); b) Expenses towards lawful medica l termination of pregnancy during the Policy Period. Note: Ectopic pregnancy is covered under ‘In -patient treatment’, provided such pregnancy is established by medical reports. Exclusions The Company shall not be liable to make any payment under the cover in respect of Maternity Expenses incurred in connection with or in respect of: 1. Covered female Insured Person below eighteen (18) years and above forty -five (45) years of age. 2. Delivery or termination within a Waiting Period of twenty -four (24) months. However, the Waiting Period may be waived only in the case of delivery, miscarriage or abortion induced by accident. 3. Delivery or lawful medical termination of pregnancy limited to two deliveries or terminations or either has been paid under the Policy an d its Renewals. 4. More than one delivery or lawful medical termination of pregnancy during a single Policy Period. 5. Maternity Expenses of Surrogate Mother, unless claim is admitted under Section 3.1.1 5 (Infertility) 6. Ectopic pregnancy 7. Pre and post hospitalisat ion expenses, other than pre and post natal treatment. 3.1.15 Infertility The Company shall pay to the hospital or reimburse the insured, in respect of the medical expenses of the insured and his spo use, if covered by the Policy , for treatment undergone as an in -patient or as a day care treatment, for procedures and/ or treatmen t of infertility, provided the Policy has been continuously in force for twenty four (24) months from the inception of the Policy or from the date of inclusion of the insured person, whichever is later. The medical expenses for either or both the insured p erson shall be subject to the limit as shown in the Table of Benefits. Exclusions The Company shall not be liable to make any payment in respect of any expenses incurred in connection with or in",
    "similarity_score": 0.7602585554122925
  },
  {
    "rank": 2,
    "text": "day care treatment, for procedures and/ or treatmen t of infertility, provided the Policy has been continuously in force for twenty four (24) months from the inception of the Policy or from the date of inclusion of the insured person, whichever is later. The medical expenses for either or both the insured p erson shall be subject to the limit as shown in the Table of Benefits. Exclusions The Company shall not be liable to make any payment in respect of any expenses incurred in connection with or in respect of 1. Insured and insured persons above forty five years of age. 2. Diagnostic tests related to infertility 3. Reversing a tubal ligation or vasectomy 4. Preserving and storing sperms, eggs and embryos 5. An egg donor or sperm donor 6. Experimental treatments 7. Any disease/ inju ry, other than traceable to maternity, of the surrogate mother. Conditions 1. Expenses for advanced procedures, including IVF, GIFT, ZIFT or ICSI, shall be payable only if the Insured person has been unable to attain or sustain a successful pregnancy throug h reasonable, and medically necessary infertility treatment. 2. Maternity expenses of the surrogate mother shall be payable under Section 3.1.14 (Maternity). Legal affidavit regarding intimation of surrogacy shall be submitted to the Company. 3. Maximum of two claims shall be admissible by the Policy during the lifetime of the insured person if he has no living child and one claim if the insured has one living child. 4. Any one illness limit shall not apply. Definitions for the purpose of the Section 1. Donor means an oocyte donor or sperm donor. 2. Embryo means a fertilized egg where cell division has commenced/ under the process and has completed the pre -embryonic stage. 3. Gamete Intra -Fallopian Transfer (GIFT) means a procedure where the sperm and egg are placed inside a catheter separated by an air bubble and then transferred to the fallopian tube. Fertilization takes place naturally. 4. Infertility means the inability to conceive after one year of unprotected sexual intercourse or the inability to sustain a succes sful pregnancy. However the one year period may be waived, provided a medical practitioner determines existence of a medical condition rendering conception impossible through unprotected sexual intercourse, including but not limited to congenital absence o f the",
    "similarity_score": 0.7170904874801636
  },
  {
    "rank": 3,
    "text": "given to the Company/TPA, and a claim has been admitted under In-patient Treatmen t Section . 3.1.11 Medical Emergency Reunion In the event of the insured person being hospitalised in a place away from the place of residence for more than five continuo us days in an intensive care unit for any life threatening condition, the Company afte r obtaining confirmation from the attending medical practitioner, of the need of a ‘family member’ to be present, shall reimburse the expenses of a round trip economy class a ir ticket for Plan B and Plan C to allow a family member, provided a claim has been admitted under In-patient Treatment Section. For the purpose of the Section, ‘family member’ shall mean spouse, children and parents of the insured person. 3.1.12 Doctor ’s Home Visit and Nursing Care d uring Post Hospitalisation The Company shall reimburse the insured, for medically necessary expenses incurred for doctor’s home visit charges, nursing ca re by qualified nurse during post hospitalisation up to the limit as shown in the Table of Benefits. 3.1.13 Anti Rabies Vaccination The Company shall reimburse the insured medically necessary expenses incurred for anti-rabies vaccination up to the limit as shown in the Table of Benefits. Hospitalisation is not required for vaccination. 3.1.14 Maternity The Company shall indemnify Maternity Expenses as described below for any female Insured Person, and also Pre -Natal and Post - Natal Hospitalisation expenses per delivery, including expenses for necessary vaccination for New Born Baby , subject to the limit National Insurance Co. Ltd. Premises No. 18 -0374, Plot no. CBD -81, New Town, Kolkata - 700156 Page 7 of 25 National Parivar Mediclaim Plus Policy UIN: NICHLIP25039V032425 as shown in the Table of Benefits. The female Insured Person should have been continuously covered for at least 24 months before availing this benefit. The New Born Baby shall be automatically covered from birth under the Sum Insured available to the mother during the corresponding Policy Period, for up to 3 months of age. On attaining 3 months of age, the New Born Baby shall be covered only if specifically included in the Policy mid-term and requisite premium paid to the Company. Cover Maternity Expenses means; a) Medical treatment expenses traceable to childbirth (including complicated deliveries and caesarean sections incurred",
    "similarity_score": 0.6799091100692749
  },
  {
    "rank": 4,
    "text": "be up to the limit as shown in the Table of Benefits , for Plan A only . However, the limit shall not apply if the treatment is undergone for a listed procedure in a Preferred Provider Network (PPN) as a package . 3.1.1.3 Treatment related to participation as a non -professional in hazardous or adventure sports Expenses related to treatme nt necessitated due to participation as a non -professional in hazardous or adventure sports, subject to Maximum amount admissible for Any One Illness shall be lower of 25% of Sum Insured. 3.1.2 Pre Hospitalisation The Company shall indemnify the medical expenses incurred up to thirty days immediately before the insured person is hospitalised, provided that: i. such medical expenses are incurred for the same condition for which the insured person’s hospitalisation was requi red, and ii. the in -patient hospitalisation claim for such hospitalisation is admissible by the Company Pre hospitalisation shall be considered as part of the Hospitalisation claim. 3.1.3 Post Hospitalisation The Company shall indemnify the medical expenses incurred up to sixty days immediately after the insured person is discharged from hospital, provided that: i. such medical expenses are incurred for the same condition for which the insured person’s hospitalisation was required, and ii. the in -patient hospitalisa tion claim for such hospitalisation is admissible by the Company Post hospitalisation shall be considered as part of the hospitalisation claim. 3.1.4 Domiciliary Hospitalisation The Company shall Company shall indemnify the medical expenses incurred under domiciliary hospitalization, including Pre Hospitalisation expenses and Post Hospitalisation expenses , up to the limit as shown in the Table of Benefits. Exclusions Domiciliary hospitalisation sh all not cover: i. Treatment of less than three days ii. Expenses incurred for alternative treatment iii. Expenses incurred for maternity or infertility iv. Expenses incurred for any of the following diseases; a) Asthma b) Bronchitis c) Chronic nephritis and nephritic syndrome d) Diarrhoea and all type of dysenteries including gastroenteritis e) Epilepsy f) Influenza, cough and cold g) All psychiatric or psychosomatic disorders h) Pyrexia of u nknown origin for less than ten days i) Tonsillitis and upper respiratory tract infection includ ing laryngitis and pharingitis j) Arthritis, gout and rheumat",
    "similarity_score": 0.6655153632164001
  },
  {
    "rank": 5,
    "text": "person) Up to 15% of SI or INR 60,000 whichever is lower Up to SI Up to SI Domiciliary Hospitalisation (as Floater) Up to INR 1,00,000 Up to INR 2,00,000 Up to INR 2,00,000 Day Care Procedures (as Floater) Up to SI Up to SI Up to SI AYUSH Treatment (as Floater) Up to SI Up to SI Up to SI Organ Donor’s Medical Expenses (as Floater) Up to SI Up to SI Up to SI Hospital Cash (per insured person, per day) INR 500, max. of 5 days INR 1,000, max. of 5 days INR 2,000, max. of 5 days Ambulance ( per insured person, in a policy year) Up to INR 2,500 Up to INR 4,000 Up to INR 5,000 Air Ambulance (per insured person, in a policy year ) Not covered Up to 5% of SI Up to 5% of SI Medical Emergency Reunion (per insured person, in a policy year) Not covered No sublimit No sublimit Doctor’s Home Visit and Nursing Care during Post Hospitalisation (per insured person, in a policy year) Not covered INR 1,000 per day, max. of 10 days INR 2,000 per day, max. of 10 days Anti Rabies Vaccination (per insured person, in a policy year) Up to INR 5,000 Up to INR 5,000 Up to INR 5,000 Maternity (including Baby from Birth Cover) (per insured person, in a policy year, waiting period of 2 years applies) Up to INR 30,000 for normal delivery and INR 50,000 for caesarean section Up to SI Up to SI Vaccination for New Born Baby As part of Maternity As part of Maternity As part of Maternity Infertility (per insured person, in a policy year , waiting period of 2 years applies ) Up to INR 50,000 Up to INR 1,00,000 Up to INR 1,00,000 Vaccination for Children, for male child up to 12 years and female child up to 14 years (per insured person, in a",
    "similarity_score": 0.6476548910140991
  },
  {
    "rank": 6,
    "text": "without any break. National Insurance Co. Ltd. Premises No. 18 -0374, Plot no. CBD -81, New Town, Kolkata - 700156 Page 5 of 25 National Parivar Mediclaim Plus Policy UIN: NICHLIP25039V032425 3 BENEFITS COVERED UNDER THE POLICY 3.1COVERAGE 3.1.1 In -patient Treatment The Company shall indemnify the medical expenses for: i. Room charges and intensive care unit charges (including diet charges, nursing care by qualified nurse, RMO charges, administration charges for IV fluids/blood transfusion/injection), subject to limit as per Section 3.1.1.1 ii. Medical practitioner(s) iii. Anaesthesia, blood, oxygen, operation theatre charges, surgical appliances iv. Medicines and drugs v. Diagnostic procedures vi. Prosthetics and other devices or equipment if implanted internally during a surgical procedure. vii. Dental treatment, necessitated due to an injury viii. Plastic surgery, necessitated due to disease or injury ix. Hormone replacement therapy, if medically necessary x. Vitamins and tonics, forming part of treatment for disease/injury as certified by the atte nding medical practitioner xi. Circumcision, necessitated for treatment of a disease or injury 3.1.1.1 Limit for Room Charges and Intensive Care Unit Charges Room charges and intensive care unit charges per day shall be payable up to the limit as shown in the Table of Benefits , for Plan A only. However, t he limit shall not apply if the treatment is undergone for a listed procedure in a Preferred Provider Network (PPN) as a package. Note: Listed procedures and Preferred Provider Network list are dynamic in nature, and will be updated in the Company’s website from time to time. 3.1.1.2 Limit for Cataract Surgery The Company’s liability for cataract surgery shall be up to the limit as shown in the Table of Benefits , for Plan A only . However, the limit shall not apply if the treatment is undergone for a listed procedure in a Preferred Provider Network (PPN) as a package . 3.1.1.3 Treatment related to participation as a non -professional in hazardous or adventure sports Expenses related to treatme nt necessitated due to participation as a non -professional in hazardous or adventure sports, subject to Maximum amount admissible for Any One",
    "similarity_score": 0.6381863355636597
  },
  {
    "rank": 7,
    "text": "Up to SI Vaccination for New Born Baby As part of Maternity As part of Maternity As part of Maternity Infertility (per insured person, in a policy year , waiting period of 2 years applies ) Up to INR 50,000 Up to INR 1,00,000 Up to INR 1,00,000 Vaccination for Children, for male child up to 12 years and female child up to 14 years (per insured person, in a policy year) Up to INR 1,000 Up to SI Up to SI Modern Treatment (12 nos) Up to 25% of SI for each treatment Up to 25% of SI for each treatment Up to 25% of SI for each treatment Treatment due to participation in hazardous or adventure sports (non -professionals) Up to 25% of SI Up to 25% of SI Up to 25% of SI Morbid Obesity Covered after waiting period of 3 years Covered after waiting period of 3 years Covered after waiting period of 3 years Refractive Error (min 7.5D) Covered after waiting period of 2 years Covered after waiting period of 2 years Covered after waiting period of 2 years Other benefits Reinstatement of sum insured due to road traffic accident Yes Yes Yes Good Health Incentives No Claim Discount 5% discount on base premium, Health Check Up (as Floater) Every 2 yrs., up to INR 5 ,000 Every 2 yrs., up to INR 7,500 Every 2 yrs., up to INR 10,000 Optional covers Pre-existing Diabetes/Hypertension (as Floater) First year Up to a maximum of 25% of SI Second year Up to a maximum of 50% of SI Third year Up to a maximum of 75% of SI Out-patient Treatment (as Floater in a policy year) Limit of cover per family - INR 2,000/ 3,000/ 4,000/ 5,000/ 10,000/ 15,000/ 20,000/ 25,000 in addition to the SI ***Critical Illness (per insured person in a policy year) Benefit amount - INR 2,00,000/ 3,00,000/ 5,00,000/ 10,00,000/ 15,00,000/",
    "similarity_score": 0.6365447044372559
  },
  {
    "rank": 8,
    "text": "malignancy o. Surgery for prolapsed intervertebral disc unless arising from accident p. Surgery of varicose vein q. Hysterectomy r. Refractive error of the eye more than 7.5 dioptres s. Congenital Internal Anomaly (not applicable for new born baby) Above diseases/treatments under 4.2.f).i, ii, iii shall be covered after the specified Waiting Period, provided they are not Pre Existing Diseases. iv. Three years waiting period Following diseas es shall be covered after three years of continuous cover f rom the inception of the policy: a. Treatment for joint replacement unless arising from accident b. Osteoarthritis and osteoporosis c. Morbid Obesity and its complications d. Stem Cell Therapy: Hematopoietic stem cells for bone marrow transplant for haematological conditions to be covered. 4.3. First 30 days waiting period (Excl 03) a) Expenses related to the treatment of any illness within thirty (30) days from the first policy commencement date shall be excluded except claims arising due to an accident, provided the same are covered. b) This exclusion shall not, however, apply if the Insured Person has Continuous Coverage for more than twelve (12) months. c) The within referred waitin g period is made applicable to the enhanced sum insured in the event of granting higher sum insured subsequently. 4.4. Investigation & Evaluation (Excl 04) a) Expenses related to any admission primarily for diagnostics and evaluation purposes only are excluded. b) Any diagnostic expenses which are not related or not incidental to the current diagnosis and treatment are excluded. 4.5. Rest Cure, Rehabilitation and Respite Care (Excl 05) a) Expenses related to any admission primarily for enforced bed rest and not for receiving treatment. This also includes: i. Custodial care either at home or in a nursing facility for personal care such as help with activities of daily living such as bathing, dressing, moving around either by skilled nurses or assistant or non -skilled persons . ii. Any services for people who are terminally ill to address physical, social, emotional and spiritual needs . 4.6. Obesity/ Weight Control (Excl 06) Expenses related to the surgical treatment of obesity that does not fulfil all the below conditions: 1) Surgery to be conducted is upon the advice of the Doctor 2) The surgery",
    "similarity_score": 0.6348064541816711
  }
]